odoo/addons/web_responsive/README.rst
odoo/addons/web_responsive/__init__.py
odoo/addons/web_responsive/__manifest__.py
odoo/addons/web_responsive/i18n/ca.po
odoo/addons/web_responsive/i18n/da.po
odoo/addons/web_responsive/i18n/de.po
odoo/addons/web_responsive/i18n/es.po
odoo/addons/web_responsive/i18n/fr.po
odoo/addons/web_responsive/i18n/hr.po
odoo/addons/web_responsive/i18n/it.po
odoo/addons/web_responsive/i18n/pt.po
odoo/addons/web_responsive/i18n/pt_BR.po
odoo/addons/web_responsive/i18n/tr.po
odoo/addons/web_responsive/i18n/web_responsive.pot
odoo/addons/web_responsive/i18n/zh_CN.po
odoo/addons/web_responsive/models/__init__.py
odoo/addons/web_responsive/models/res_users.py
odoo/addons/web_responsive/readme/CONTRIBUTORS.rst
odoo/addons/web_responsive/readme/DESCRIPTION.rst
odoo/addons/web_responsive/readme/ROADMAP.rst
odoo/addons/web_responsive/readme/USAGE.rst
odoo/addons/web_responsive/static/description/icon.png
odoo/addons/web_responsive/static/description/index.html
odoo/addons/web_responsive/static/img/appmenu.gif
odoo/addons/web_responsive/static/img/big_checkboxes.gif
odoo/addons/web_responsive/static/img/chatter.gif
odoo/addons/web_responsive/static/img/chatter_topbar.gif
odoo/addons/web_responsive/static/img/document_viewer.gif
odoo/addons/web_responsive/static/img/formview.gif
odoo/addons/web_responsive/static/img/listview.gif
odoo/addons/web_responsive/static/src/css/web_responsive.scss
odoo/addons/web_responsive/static/src/js/web_responsive.js
odoo/addons/web_responsive/static/src/xml/apps.xml
odoo/addons/web_responsive/static/src/xml/document_viewer.xml
odoo/addons/web_responsive/static/src/xml/form_view.xml
odoo/addons/web_responsive/static/src/xml/menu.xml
odoo/addons/web_responsive/static/src/xml/navbar.xml
odoo/addons/web_responsive/tests/__init__.py
odoo/addons/web_responsive/tests/test_res_users.py
odoo/addons/web_responsive/views/assets.xml
odoo/addons/web_responsive/views/res_users.xml
odoo/addons/web_responsive/views/web.xml
odoo12_addon_web_responsive-12.0.2.4.1.dist-info/METADATA
odoo12_addon_web_responsive-12.0.2.4.1.dist-info/WHEEL
odoo12_addon_web_responsive-12.0.2.4.1.dist-info/top_level.txt
odoo12_addon_web_responsive-12.0.2.4.1.dist-info/RECORD
