Metadata-Version: 2.1
Name: odoo12-addon-web-responsive
Version: 12.0.2.4.1
Summary: Responsive web client, community-supported
Home-page: https://github.com/OCA/web
Author: LasLabs, Tecnativa, Alexandre Díaz, Odoo Community Association (OCA)
Author-email: support@odoo-community.org
License: LGPL-3
Platform: UNKNOWN
Classifier: Programming Language :: Python
Classifier: Framework :: Odoo
Classifier: Framework :: Odoo :: 12.0
Classifier: License :: OSI Approved :: GNU Lesser General Public License v3 (LGPLv3)
Requires-Python: >=3.5
Requires-Dist: odoo (<12.1dev,>=12.0a)
